RGAST/RGAST.py
RGAST/Train_RGAST.py
RGAST/__init__.py
RGAST/svg.py
RGAST/utils.py
RGAST-0.0.2.dist-info/LICENSE
RGAST-0.0.2.dist-info/METADATA
RGAST-0.0.2.dist-info/WHEEL
RGAST-0.0.2.dist-info/top_level.txt
RGAST-0.0.2.dist-info/RECORD
