Metadata-Version: 2.1
Name: RGAST
Version: 0.0.2
Summary: Relational Graph Attention Network for Spatial Transcriptome Analysis
Home-page: https://github.com/GYQ-form/RGAST
Author: Yuqiao Gong
Author-email: gyq123@sjtu.edu.cn
License: MIT
Keywords: spatial transcriptomic,RGAT,representation learning,spatial domain identification
Classifier: Programming Language :: Python :: 3
Classifier: License :: OSI Approved :: MIT License
Classifier: Operating System :: OS Independent
License-File: LICENSE
Requires-Dist: torch
Requires-Dist: scanpy
Requires-Dist: scikit-learn
Requires-Dist: torch-geometric
Requires-Dist: scipy
Requires-Dist: numba
